{ "height":48,
 "infinite":false,
 "layers":[
        {
         "compression":"zlib",
         "data":"eJztlOEKwCAIhNX3f+j92UDCRM9qW3RwPyI+LexiIuLj46I9odxX+Gi9Kj\/iPpEaM+dpWTbjs3X+znPDWDwilNO93+Bn5r83K7r3KtldlRnZkLeEzlHzVj2k\/7MWwnnN9jLv8VllOe8vWtHfOsuo7EvAmTcc9QXTvAH3",
         "encoding":"base64",
         "height":48,
         "name":"tiles",
         "opacity":1,
         "type":"tilelayer",
         "visible":true,
         "width":16,
         "x":0,
         "y":0
        }, 
        {
         "draworder":"topdown",
         "name":"things",
         "objects":[
                {
                 "height":16,
                 "id":77,
                 "name":"elevator",
                 "rotation":0,
                 "type":"",
                 "visible":true,
                 "width":32,
                 "x":112,
                 "y":640
                }, 
                {
                 "height":16,
                 "id":80,
                 "name":"fragile_block",
                 "rotation":0,
                 "type":"",
                 "visible":true,
                 "width":16,
                 "x":0,
                 "y":704
                }, 
                {
                 "height":16,
                 "id":81,
                 "name":"fragile_block",
                 "rotation":0,
                 "type":"",
                 "visible":true,
                 "width":16,
                 "x":0,
                 "y":672
                }, 
                {
                 "height":16,
                 "id":82,
                 "name":"fragile_block",
                 "rotation":0,
                 "type":"",
                 "visible":true,
                 "width":16,
                 "x":0,
                 "y":688
                }, 
                {
                 "height":16,
                 "id":83,
                 "name":"elevator",
                 "rotation":0,
                 "type":"",
                 "visible":true,
                 "width":32,
                 "x":160,
                 "y":384
                }],
         "opacity":1,
         "type":"objectgroup",
         "visible":true,
         "x":0,
         "y":0
        }],
 "nextobjectid":84,
 "orientation":"orthogonal",
 "renderorder":"right-down",
 "tiledversion":"1.1.5",
 "tileheight":16,
 "tilesets":[
        {
         "firstgid":1,
         "source":"..\/tiles-editor.tsx"
        }],
 "tilewidth":16,
 "type":"map",
 "version":1,
 "width":16
}