{ "height":48,
 "infinite":false,
 "layers":[
        {
         "compression":"zlib",
         "data":"eJztldEOhSAIhq278\/4v3FVbYwb\/j4ingo2tJvChImytta2jUno2mj7NP1uKX\/zir+dr671vJv6I\/yrJznW0r0fE9HCkjeUTPX9YvpUDy+7xR+5nNv+6jvJ\/N6rxNR9pa90FUzNoTTO1H9Gb2XxnCXoOWbKSH9mHsvnoG0fZrDDxETuWHXVH\/8L39LeZ\/Cxhe\/\/X+Yyesgtl+CN7YmyLX\/y38q\/\/6PtG87ybEUyeXn8trhVHO2cvP3NuSS5yN9aevTXI8tn54WF663iV\/wHvggJL",
         "encoding":"base64",
         "height":48,
         "name":"tiles",
         "opacity":1,
         "type":"tilelayer",
         "visible":true,
         "width":32,
         "x":0,
         "y":0
        }, 
        {
         "draworder":"topdown",
         "name":"things",
         "objects":[
                {
                 "height":16,
                 "id":79,
                 "name":"elevator",
                 "rotation":0,
                 "type":"",
                 "visible":true,
                 "width":32,
                 "x":448,
                 "y":608
                }, 
                {
                 "height":16,
                 "id":81,
                 "name":"bonus_life",
                 "rotation":0,
                 "type":"",
                 "visible":true,
                 "width":16,
                 "x":48,
                 "y":288
                }],
         "opacity":1,
         "type":"objectgroup",
         "visible":true,
         "x":0,
         "y":0
        }],
 "nextobjectid":82,
 "orientation":"orthogonal",
 "renderorder":"right-down",
 "tiledversion":"1.1.5",
 "tileheight":16,
 "tilesets":[
        {
         "firstgid":1,
         "source":"..\/tiles-editor.tsx"
        }],
 "tilewidth":16,
 "type":"map",
 "version":1,
 "width":32
}