{ "height":48,
 "layers":[
        {
         "compression":"zlib",
         "data":"eJztlFEOwzAIQ9Ob7f6nqjTtI6oSDNgknVpLfKXhYSA9WmvHG2900SuZ4\/OLFNPik3V5PX\/rN8oa3lfxGWVm68gJ+5FRgC\/tUZ\/X4qA+svNj9nl2Z+THOs\/yPftr1a1gWnxlbub97q7jKf5XcWeMCv+jXIiR4VdqF1+xu\/9Uh+IdVEj5lqu5FgedKfnWvwZ5VfGRnxmjgq\/opdr\/6hqe5n\/GXlXTSKtn4pF6fqys3jF7p1CV\/4p5obsoZ4TPiJlp5K1V8T05GTaaVybv9Tt01+st4ie7P1kGy6\/gRnt9xzgBLr0FXQ==",
         "encoding":"base64",
         "height":48,
         "name":"tiles",
         "opacity":1,
         "type":"tilelayer",
         "visible":true,
         "width":32,
         "x":0,
         "y":0
        }],
 "nextobjectid":1,
 "orientation":"orthogonal",
 "renderorder":"right-down",
 "tileheight":16,
 "tilesets":[
        {
         "firstgid":1,
         "source":"..\/tiles-editor.tsx"
        }],
 "tilewidth":16,
 "version":1,
 "width":32
}